ainalyn/__init__.py
ainalyn/_version.py
ainalyn/api.py
ainalyn/cli.py
ainalyn/py.typed
ainalyn/adapters/__init__.py
ainalyn/adapters/inbound/__init__.py
ainalyn/adapters/inbound/builders.py
ainalyn/adapters/inbound/errors.py
ainalyn/adapters/inbound/builders/__init__.py
ainalyn/adapters/inbound/builders/agent_builder.py
ainalyn/adapters/inbound/builders/module_builder.py
ainalyn/adapters/inbound/builders/node_builder.py
ainalyn/adapters/inbound/builders/prompt_builder.py
ainalyn/adapters/inbound/builders/tool_builder.py
ainalyn/adapters/inbound/builders/workflow_builder.py
ainalyn/adapters/outbound/__init__.py
ainalyn/adapters/outbound/http_platform_client.py
ainalyn/adapters/outbound/json_exporter.py
ainalyn/adapters/outbound/mock_platform_client.py
ainalyn/adapters/outbound/schema_validator.py
ainalyn/adapters/outbound/static_analyzer.py
ainalyn/adapters/outbound/yaml_serializer.py
ainalyn/application/__init__.py
ainalyn/application/services.py
ainalyn/application/ports/__init__.py
ainalyn/application/ports/inbound/__init__.py
ainalyn/application/ports/inbound/validate_agent_definition.py
ainalyn/application/ports/outbound/__init__.py
ainalyn/application/ports/outbound/definition_persistence.py
ainalyn/application/ports/outbound/definition_schema_validation.py
ainalyn/application/ports/outbound/definition_serialization.py
ainalyn/application/ports/outbound/definition_static_analysis.py
ainalyn/application/ports/outbound/platform_submission.py
ainalyn/application/use_cases/__init__.py
ainalyn/application/use_cases/compile_definition.py
ainalyn/application/use_cases/export_definition.py
ainalyn/application/use_cases/submit_definition.py
ainalyn/application/use_cases/validate_definition.py
ainalyn/domain/__init__.py
ainalyn/domain/errors.py
ainalyn/domain/entities/__init__.py
ainalyn/domain/entities/agent_definition.py
ainalyn/domain/entities/agent_type.py
ainalyn/domain/entities/behavior_config.py
ainalyn/domain/entities/display_info.py
ainalyn_sdk-0.2.0a2.dist-info/METADATA
ainalyn_sdk-0.2.0a2.dist-info/WHEEL
ainalyn_sdk-0.2.0a2.dist-info/entry_points.txt
ainalyn_sdk-0.2.0a2.dist-info/licenses/LICENSE
ainalyn_sdk-0.2.0a2.dist-info/RECORD
