Metadata-Version: 2.4
Name: ainalyn-sdk
Version: 0.2.0a2
Summary: Agent Definition Compiler for Ainalyn Platform
Project-URL: Homepage, https://github.com/CoreNovus/ainalyn-sdk
Project-URL: Documentation, https://docs.ainalyn.corenovus.com
Project-URL: Repository, https://github.com/CoreNovus/ainalyn-sdk
Project-URL: Issues, https://github.com/CoreNovus/ainalyn-sdk/issues
Author-email: CoreNovus <dev@corenovus.com>
License: MIT
License-File: LICENSE
Keywords: agent,ainalyn,marketplace,sdk,task-oriented,workflow
Classifier: Development Status :: 3 - Alpha
Classifier: Intended Audience :: Developers
Classifier: License :: OSI Approved :: MIT License
Classifier: Operating System :: OS Independent
Classifier: Programming Language :: Python :: 3
Classifier: Programming Language :: Python :: 3.11
Classifier: Programming Language :: Python :: 3.12
Classifier: Programming Language :: Python :: 3.13
Classifier: Topic :: Software Development :: Libraries :: Python Modules
Classifier: Typing :: Typed
Requires-Python: >=3.11
Requires-Dist: pyyaml>=6.0
Provides-Extra: all
Requires-Dist: coverage[toml]>=7.3.0; extra == 'all'
Requires-Dist: ipython>=8.0.0; extra == 'all'
Requires-Dist: mkdocs-material>=9.5.0; extra == 'all'
Requires-Dist: mkdocs>=1.5.0; extra == 'all'
Requires-Dist: mkdocstrings[python]>=0.24.0; extra == 'all'
Requires-Dist: mypy>=1.7.0; extra == 'all'
Requires-Dist: pre-commit>=3.6.0; extra == 'all'
Requires-Dist: pytest-cov>=4.1.0; extra == 'all'
Requires-Dist: pytest>=7.4.0; extra == 'all'
Requires-Dist: ruff>=0.1.8; extra == 'all'
Provides-Extra: dev
Requires-Dist: coverage[toml]>=7.3.0; extra == 'dev'
Requires-Dist: ipython>=8.0.0; extra == 'dev'
Requires-Dist: mypy>=1.7.0; extra == 'dev'
Requires-Dist: pre-commit>=3.6.0; extra == 'dev'
Requires-Dist: pytest-cov>=4.1.0; extra == 'dev'
Requires-Dist: pytest>=7.4.0; extra == 'dev'
Requires-Dist: ruff>=0.1.8; extra == 'dev'
Provides-Extra: docs
Requires-Dist: mkdocs-material>=9.5.0; extra == 'docs'
Requires-Dist: mkdocs>=1.5.0; extra == 'docs'
Requires-Dist: mkdocstrings[python]>=0.24.0; extra == 'docs'
Provides-Extra: lint
Requires-Dist: ruff>=0.1.8; extra == 'lint'
Provides-Extra: test
Requires-Dist: coverage[toml]>=7.3.0; extra == 'test'
Requires-Dist: pytest-cov>=4.1.0; extra == 'test'
Requires-Dist: pytest>=7.4.0; extra == 'test'
Provides-Extra: type
Requires-Dist: mypy>=1.7.0; extra == 'type'
